polyaxon_deploy/__init__.py
polyaxon_deploy/logger.py
polyaxon_deploy/pkg.py
polyaxon_deploy/apps/__init__.py
polyaxon_deploy/apps/middlewares.py
polyaxon_deploy/apps/sandbox.py
polyaxon_deploy/apps/streams.py
polyaxon_deploy/cli/__init__.py
polyaxon_deploy/cli/sandbox.py
polyaxon_deploy/cli/streams.py
polyaxon_deploy/connections/__init__.py
polyaxon_deploy/connections/fs.py
polyaxon_deploy/controllers/__init__.py
polyaxon_deploy/controllers/events.py
polyaxon_deploy/controllers/k8s_check.py
polyaxon_deploy/controllers/k8s_crd.py
polyaxon_deploy/controllers/k8s_pods.py
polyaxon_deploy/controllers/logs.py
polyaxon_deploy/controllers/notebooks.py
polyaxon_deploy/controllers/uploads.py
polyaxon_deploy/endpoints/__init__.py
polyaxon_deploy/endpoints/artifacts.py
polyaxon_deploy/endpoints/base.py
polyaxon_deploy/endpoints/events.py
polyaxon_deploy/endpoints/index.py
polyaxon_deploy/endpoints/k8s.py
polyaxon_deploy/endpoints/logs.py
polyaxon_deploy/endpoints/notifications.py
polyaxon_deploy/endpoints/sandbox.py
polyaxon_deploy/endpoints/utils.py
polyaxon_deploy/runners/__init__.py
polyaxon_deploy/runners/base.py
polyaxon_deploy/runners/sandbox.py
polyaxon_deploy/runners/streams.py
polyaxon_deploy/tasks/__init__.py
polyaxon_deploy/tasks/logs.py
polyaxon_deploy/tasks/notification.py
polyaxon_deploy-1.0.2.dist-info/METADATA
polyaxon_deploy-1.0.2.dist-info/WHEEL
polyaxon_deploy-1.0.2.dist-info/top_level.txt
polyaxon_deploy-1.0.2.dist-info/RECORD
