Metadata-Version: 2.1
Name: polyaxon-deploy
Version: 1.0.2
Summary: Polyaxon deployment and serving tools: streams, sandbox, ML-API, and spaces.
Home-page: https://github.com/polyaxon/polyaxon
Author: Polyaxon, Inc.
Author-email: contact@polyaxon.com
Maintainer: Polyaxon, Inc.
Maintainer-email: contact@polyaxon.com
License: Apache 2.0
Keywords: polyaxon,aws,s3,microsoft,azure,google cloud storage,gcs,deep-learning,machine-learning,data-science,neural-networks,artificial-intelligence,ai,reinforcement-learning,kubernetes,aws,microsoft,azure,google cloud,tensorFlow,pytorch,matplotlib,plotly,visualization,analytics,hyperopt,scikit-learn,optimization,bayesian-optimization
Platform: any
Classifier: Programming Language :: Python
Classifier: Programming Language :: Python :: 3
Classifier: Programming Language :: Python :: 3.5
Classifier: Programming Language :: Python :: 3.6
Classifier: Programming Language :: Python :: 3.7
Classifier: Programming Language :: Python :: 3.8
Classifier: Operating System :: OS Independent
Classifier: Intended Audience :: Developers
Classifier: Intended Audience :: Science/Research
Classifier: Topic :: Scientific/Engineering :: Artificial Intelligence
Requires-Python: >=3.5
Requires-Dist: fsspec (==2022.5.0)
Requires-Dist: aiofiles (==0.8.0)
Requires-Dist: kubernetes-asyncio (<22.6.0,>=12.1.1)
Requires-Dist: nbconvert (>=6.5.0)
Requires-Dist: python-multipart (==0.0.5)
Requires-Dist: pandas (==1.3.4)
Requires-Dist: starlette (==0.18.0)
Requires-Dist: uvicorn[standard] (==0.17.6)
Requires-Dist: uvloop (==0.16.0)
Provides-Extra: dev
Requires-Dist: numpy (<=1.23) ; extra == 'dev'
Requires-Dist: pandas ; extra == 'dev'
Provides-Extra: fs
Requires-Dist: adlfs (==2022.7.0) ; extra == 'fs'
Requires-Dist: fsspec (==2022.5.0) ; extra == 'fs'
Requires-Dist: gcsfs (==2022.5.0) ; extra == 'fs'
Requires-Dist: s3fs (==2022.5.0) ; extra == 'fs'
